{
  "junctions": {
    "100": {
      "demand_a": 0.001016988730119947,
      "demand_b": 0.001017058885179084,
      "demand_lb": 1e-06,
      "head_a": 106.20917515030345,
      "head_a_tag": "",
      "head_b": 106.20916780168125,
      "head_b_tag": "",
      "head_lb": 86.77221610776621,
      "head_ub": 153.2277838922338
    },
    "110": {
      "demand_a": 0.0009274561035773829,
      "demand_b": 0.000927564132815098,
      "demand_lb": 1e-06,
      "head_a": 106.04612926256533,
      "head_a_tag": "",
      "head_b": 106.0461216367554,
      "head_b_tag": "",
      "head_lb": 86.21560255826124,
      "head_ub": 153.78439744173875
    },
    "115": {
      "demand_a": 0.01567368735018659,
      "demand_b": 0.015673536573696117,
      "demand_lb": 1e-06,
      "head_a": 105.57058573516585,
      "head_a_tag": "",
      "head_b": 105.57058573516585,
      "head_b_tag": "",
      "head_lb": 79.16562740980649,
      "head_ub": 160.8343725901935
    },
    "120": {
      "demand_a": 0.022972774500821927,
      "demand_b": 0.022971952611008695,
      "demand_lb": 1e-06,
      "head_a": 105.68142528391144,
      "head_a_tag": "",
      "head_b": 105.68142230097797,
      "head_b_tag": "",
      "head_lb": 81.42322008686486,
      "head_ub": 158.57677991313514
    },
    "130": {
      "demand_a": 0.02379638855577671,
      "demand_b": 0.023795238630417343,
      "demand_lb": 1e-06,
      "head_a": 105.43680147479881,
      "head_a_tag": "",
      "head_b": 105.43680681348911,
      "head_b_tag": "",
      "head_lb": 77.894500084227,
      "head_ub": 162.105499915773
    },
    "140": {
      "demand_a": 0.014594387395970645,
      "demand_b": 0.01459156178158745,
      "demand_lb": 1e-06,
      "head_a": 105.8193278515902,
      "head_a_tag": "",
      "head_b": 105.81934023123962,
      "head_b_tag": "",
      "head_lb": 82.98206548445219,
      "head_ub": 157.0179345155478
    },
    "150": {
      "demand_a": 0.023837971358930562,
      "demand_b": 0.023838212956199464,
      "demand_lb": 1e-06,
      "head_a": 106.02386471934321,
      "head_a_tag": "",
      "head_b": 106.0238607837157,
      "head_b_tag": "",
      "head_lb": 86.31055161768435,
      "head_ub": 153.68944838231565
    },
    "160": {
      "demand_a": 0.0222566566020804,
      "demand_b": 0.022259474787609486,
      "demand_lb": 1e-06,
      "head_a": 105.73910413540388,
      "head_a_tag": "",
      "head_b": 105.73909596451406,
      "head_b_tag": "",
      "head_lb": 82.35922656162961,
      "head_ub": 157.6407734383704
    },
    "170": {
      "demand_a": 0.02237112941603173,
      "demand_b": 0.022371423239199356,
      "demand_lb": 1e-06,
      "head_a": 105.05441943247497,
      "head_a_tag": "",
      "head_b": 105.05441518529133,
      "head_b_tag": "",
      "head_lb": 71.54969951960152,
      "head_ub": 168.45030048039848
    },
    "20": {
      "demand_a": 0.0036041324592638035,
      "demand_b": 0.003604018038339263,
      "demand_lb": 1e-06,
      "head_a": 119.11434918107919,
      "head_a_tag": "",
      "head_b": 119.11434918107919,
      "head_b_tag": "",
      "head_lb": 116.00248141431898,
      "head_ub": 123.99751858568102
    },
    "30": {
      "demand_a": 0.0011240832821259594,
      "demand_b": 0.0011323800430886322,
      "demand_lb": 1e-06,
      "head_a": 106.73127598795689,
      "head_a_tag": "",
      "head_b": 106.73125303100889,
      "head_b_tag": "",
      "head_lb": 88.12841938729362,
      "head_ub": 151.87158061270637
    },
    "40": {
      "demand_a": 0.0009193272694603405,
      "demand_b": 0.0009170492821952668,
      "demand_lb": 1e-06,
      "head_a": 106.57151998668778,
      "head_a_tag": "",
      "head_b": 106.57155053816432,
      "head_b_tag": "",
      "head_lb": 86.21957276930736,
      "head_ub": 153.78042723069262
    },
    "50": {
      "demand_a": 0.0009745062756200476,
      "demand_b": 0.00096530647704101,
      "demand_lb": 1e-06,
      "head_a": 106.42543043793034,
      "head_a_tag": "",
      "head_b": 106.4254791779704,
      "head_b_tag": "",
      "head_lb": 85.28339347541171,
      "head_ub": 154.7166065245883
    },
    "55": {
      "demand_a": 0.01533703875213083,
      "demand_b": 0.015338034085910186,
      "demand_lb": 1e-06,
      "head_a": 105.68076377646017,
      "head_a_tag": "",
      "head_b": 105.68075635506423,
      "head_b_tag": "",
      "head_lb": 78.26879460181607,
      "head_ub": 161.73120539818393
    },
    "60": {
      "demand_a": 0.0009210672017996233,
      "demand_b": 0.0009206472557255763,
      "demand_lb": 1e-06,
      "head_a": 106.57482127706494,
      "head_a_tag": "",
      "head_b": 106.57481174512385,
      "head_b_tag": "",
      "head_lb": 87.73489530174572,
      "head_ub": 152.26510469825428
    },
    "70": {
      "demand_a": 0.0010921365432919744,
      "demand_b": 0.0010920882497098827,
      "demand_lb": 1e-06,
      "head_a": 106.78262505012532,
      "head_a_tag": "",
      "head_b": 106.78261470326542,
      "head_b_tag": "",
      "head_lb": 88.22899350411438,
      "head_ub": 151.77100649588562
    },
    "75": {
      "demand_a": 0.015927131974087693,
      "demand_b": 0.01592804762607008,
      "demand_lb": 1e-06,
      "head_a": 105.59062861867613,
      "head_a_tag": "",
      "head_b": 105.59062298475885,
      "head_b_tag": "",
      "head_lb": 79.57763110703831,
      "head_ub": 160.42236889296169
    },
    "80": {
      "demand_a": 0.0007497014475744898,
      "demand_b": 0.0007525525828353599,
      "demand_lb": 1e-06,
      "head_a": 106.2827614582618,
      "head_a_tag": "",
      "head_b": 106.2827614582618,
      "head_b_tag": "",
      "head_lb": 87.02947368089687,
      "head_ub": 152.97052631910313
    },
    "90": {
      "demand_a": 0.0010234592238220486,
      "demand_b": 0.0010238772040453634,
      "demand_lb": 1e-06,
      "head_a": 106.33741421292791,
      "head_a_tag": "",
      "head_b": 106.33740685998089,
      "head_b_tag": "",
      "head_lb": 87.1110458474528,
      "head_ub": 152.8889541525472
    }
  },
  "metadata": {
    "DEMAND_INTERVALS": false,
    "DEMAND_LB": 1e-06,
    "FIX_TOTAL_DEMAND": true,
    "GLOBAL_SOLVER": "couenne",
    "HEADLOSS_MODEL": "hw",
    "MEASUREMENT_HEADS_EQUAL_ONLY": true,
    "MEASUREMENT_SITES": [
      "115",
      "80"
    ],
    "MULTI_STARTS": 10,
    "MULTI_START_NOISE": 0.05,
    "NORM": 2,
    "PIPE_BOUNDS": true,
    "PIPE_BOUND_METHOD": "perturb",
    "PIPE_BOUND_PERTURB_BASE": "base",
    "PIPE_BOUND_PERTURB_FIX_TOTAL": true,
    "PIPE_BOUND_PERTURB_SAMPLES": 25,
    "PIPE_BOUND_PERTURB_SEED": 1,
    "PIPE_BOUND_PERTURB_SIGMA": 0.1,
    "PIPE_BOUND_POLICY": "minmax",
    "PIPE_BOUND_SAFENESS": 0.85,
    "RADIUS": true,
    "SCENARIO_SOURCE": "base",
    "SINGLE_NODE_SOLUTION": false,
    "SOLVER": "hexaly_xd",
    "USE_RESERVOIR_OUTFLOW_CONSTRAINT": false,
    "WDN_NAME": "Anytown",
    "output_dir": "data/Anytown-B-batch-20260331-165254/115_80",
    "timestamp": "20260331-165254"
  },
  "output_dir": "data/Anytown-B-batch-20260331-165254/115_80",
  "pipes": {
    "1": {
      "flow_a": 0.18912002444267273,
      "flow_a_tag": "lb",
      "flow_b": 0.18912002444267273,
      "flow_b_tag": "lb",
      "flow_lb": 0.18912002444267273,
      "flow_ub": 0.18912002444267273,
      "headloss_res_a": -3.111867766760211,
      "headloss_res_b": -3.111867766760211
    },
    "10": {
      "flow_a": 0.0366396972682417,
      "flow_a_tag": "",
      "flow_b": 0.03663959382979439,
      "flow_b_tag": "",
      "flow_lb": 0.03621004894375801,
      "flow_ub": 0.037094879895448685,
      "headloss_res_a": -0.8699597204143747,
      "headloss_res_b": -0.8699545688118466
    },
    "12": {
      "flow_a": 0.019785071313528173,
      "flow_a_tag": "",
      "flow_b": 0.019784999472797726,
      "flow_b_tag": "",
      "flow_lb": 0.01969151757657528,
      "flow_ub": 0.019883129745721817,
      "headloss_res_a": -0.7552964177137875,
      "headloss_res_b": -0.7552906934208818
    },
    "14": {
      "flow_a": 0.021179524774827173,
      "flow_a_tag": "",
      "flow_b": 0.02117947992750337,
      "flow_b_tag": "",
      "flow_lb": 0.020930293947458267,
      "flow_ub": 0.021436985582113266,
      "headloss_res_a": -0.27449734037115325,
      "headloss_res_b": -0.27449611276147656
    },
    "16": {
      "flow_a": 0.014089334734695836,
      "flow_a_tag": "",
      "flow_b": 0.014089264909392859,
      "flow_b_tag": "",
      "flow_lb": 0.013912584632635117,
      "flow_ub": 0.014262482523918152,
      "headloss_res_a": -0.37138715994530835,
      "headloss_res_b": -0.3713833047104187
    },
    "18": {
      "flow_a": 0.02545257657022582,
      "flow_a_tag": "",
      "flow_b": 0.025452128027759115,
      "flow_b_tag": "",
      "flow_lb": 0.025259651243686676,
      "flow_ub": 0.025614239275455475,
      "headloss_res_a": -0.40448545112796885,
      "headloss_res_b": -0.40447043330453736
    },
    "2": {
      "flow_a": 0.08099757841916129,
      "flow_a_tag": "",
      "flow_b": 0.0809976151149086,
      "flow_b_tag": "",
      "flow_lb": 0.0807003304362297,
      "flow_ub": 0.08126632869243622,
      "headloss_res_a": -15.25837194830164,
      "headloss_res_b": -15.25838660069341
    },
    "20": {
      "flow_a": 0.006374732830092578,
      "flow_a_tag": "",
      "flow_b": 0.0063742697204492655,
      "flow_b_tag": "",
      "flow_lb": 0.00594573887065053,
      "flow_ub": 0.006846603937447071,
      "headloss_res_a": -0.06997464244591908,
      "headloss_res_b": -0.0699638882645369
    },
    "22": {
      "flow_a": 0.016372839341686984,
      "flow_a_tag": "",
      "flow_b": 0.01637274298905372,
      "flow_b_tag": "",
      "flow_lb": 0.016077831387519836,
      "flow_ub": 0.016797976568341255,
      "headloss_res_a": -0.508574928613932,
      "headloss_res_b": -0.508568669710749
    },
    "24": {
      "flow_a": 0.010103374652622397,
      "flow_a_tag": "",
      "flow_b": 0.01010337446864224,
      "flow_b_tag": "",
      "flow_lb": 0.009536479599773884,
      "flow_ub": 0.010511047206819057,
      "headloss_res_a": -0.18481724924962523,
      "headloss_res_b": -0.18481724217307455
    },
    "26": {
      "flow_a": 0.019909091224074617,
      "flow_a_tag": "",
      "flow_b": 0.0199088932318894,
      "flow_b_tag": "",
      "flow_lb": 0.01894422248005867,
      "flow_ub": 0.020829951390624046,
      "headloss_res_a": -0.240865300508396,
      "headloss_res_b": -0.24086023706950788
    },
    "28": {
      "flow_a": 0.014764224851374672,
      "flow_a_tag": "",
      "flow_b": 0.014764346038241548,
      "flow_b_tag": "",
      "flow_lb": 0.014291252009570599,
      "flow_ub": 0.015310738235712051,
      "headloss_res_a": -0.40961778998213705,
      "headloss_res_b": -0.4096248289251949
    },
    "30": {
      "flow_a": 0.019283453731894107,
      "flow_a_tag": "",
      "flow_b": 0.019282560265374185,
      "flow_b_tag": "",
      "flow_lb": 0.01899469830095768,
      "flow_ub": 0.019574880599975586,
      "headloss_res_a": -1.6649348414523224,
      "headloss_res_b": -1.664779488302884
    },
    "32": {
      "flow_a": 0.019502102668916853,
      "flow_a_tag": "",
      "flow_b": 0.019498575397318328,
      "flow_b_tag": "",
      "flow_lb": 0.01927671954035759,
      "flow_ub": 0.019740989431738853,
      "headloss_res_a": -1.7031720307522717,
      "headloss_res_b": -1.7025517186141583
    },
    "34": {
      "flow_a": 0.027693225796452586,
      "flow_a_tag": "",
      "flow_b": 0.027689720258033224,
      "flow_b_tag": "",
      "flow_lb": 0.0273591261357069,
      "flow_ub": 0.028005842119455338,
      "headloss_res_a": -3.4506276452906306,
      "headloss_res_b": -3.44974837847682
    },
    "36": {
      "flow_a": 0.018582775399456512,
      "flow_a_tag": "",
      "flow_b": 0.01858152611512306,
      "flow_b_tag": "",
      "flow_lb": 0.018348271027207375,
      "flow_ub": 0.01881066896021366,
      "headloss_res_a": -1.5453417259175295,
      "headloss_res_b": -1.5451324987675117
    },
    "38": {
      "flow_a": 0.018346559869501948,
      "flow_a_tag": "",
      "flow_b": 0.018349943912404115,
      "flow_b_tag": "",
      "flow_lb": 0.017696484923362732,
      "flow_ub": 0.018880587071180344,
      "headloss_res_a": -1.5060342386252095,
      "headloss_res_b": -1.5065937648776546
    },
    "4": {
      "flow_a": 0.06530171696011725,
      "flow_a_tag": "",
      "flow_b": 0.06530178232871113,
      "flow_b_tag": "",
      "flow_lb": 0.06507140398025513,
      "flow_ub": 0.06550092995166779,
      "headloss_res_a": -129.76455924906273,
      "headloss_res_b": -129.7648208786751
    },
    "40": {
      "flow_a": 0.03465994297087118,
      "flow_a_tag": "",
      "flow_b": 0.03465944303953559,
      "flow_b_tag": "",
      "flow_lb": 0.03409574180841446,
      "flow_ub": 0.0352771021425724,
      "headloss_res_a": -5.42078621139414,
      "headloss_res_b": -5.420628845544577
    },
    "42": {
      "flow_a": 0.012391979793778533,
      "flow_a_tag": "",
      "flow_b": 0.012391446052808829,
      "flow_b_tag": "",
      "flow_lb": 0.011307762935757637,
      "flow_ub": 0.01329136360436678,
      "headloss_res_a": -2.6887338213271055,
      "headloss_res_b": -2.688500907042299
    },
    "44": {
      "flow_a": 0.014816204264427178,
      "flow_a_tag": "",
      "flow_b": 0.01481632325017637,
      "flow_b_tag": "",
      "flow_lb": 0.013517831452190876,
      "flow_ub": 0.016134459525346756,
      "headloss_res_a": -3.851249488800004,
      "headloss_res_b": -3.8513116846187545
    },
    "46": {
      "flow_a": 0.019421228438492942,
      "flow_a_tag": "",
      "flow_b": 0.019421246782129545,
      "flow_b_tag": "",
      "flow_lb": 0.018659140914678574,
      "flow_ub": 0.02026054821908474,
      "headloss_res_a": -6.6365158250853895,
      "headloss_res_b": -6.636528427376218
    },
    "48": {
      "flow_a": 0.006395763528176591,
      "flow_a_tag": "",
      "flow_b": 0.0063957693992386,
      "flow_b_tag": "",
      "flow_lb": 0.005763679277151823,
      "flow_ub": 0.007044963072985411,
      "headloss_res_a": -0.2957094476457484,
      "headloss_res_b": -0.2957100126974997
    },
    "50": {
      "flow_a": 0.02775084563199472,
      "flow_a_tag": "",
      "flow_b": 0.027750872234424195,
      "flow_b_tag": "",
      "flow_lb": 0.027486592531204224,
      "flow_ub": 0.028059057891368866,
      "headloss_res_a": -3.4650961219173952,
      "headloss_res_b": -3.4651028088792946
    },
    "52": {
      "flow_a": 0.016934058396734872,
      "flow_a_tag": "",
      "flow_b": 0.016933941992713017,
      "flow_b_tag": "",
      "flow_lb": 0.016400272026658058,
      "flow_ub": 0.017505863681435585,
      "headloss_res_a": -5.038231488421687,
      "headloss_res_b": -5.038161852440491
    },
    "54": {
      "flow_a": 0.019688003735330282,
      "flow_a_tag": "",
      "flow_b": 0.019687047533707962,
      "flow_b_tag": "",
      "flow_lb": 0.016385603696107864,
      "flow_ub": 0.02289876528084278,
      "headloss_res_a": -0.6342446600728697,
      "headloss_res_b": -0.6341826393546837
    },
    "56": {
      "flow_a": 0.013649287631243226,
      "flow_a_tag": "",
      "flow_b": 0.013649036915412287,
      "flow_b_tag": "",
      "flow_lb": 0.012008121237158775,
      "flow_ub": 0.015087492763996124,
      "headloss_res_a": -3.265542113075764,
      "headloss_res_b": -3.26542148348873
    },
    "58": {
      "flow_a": 0.02751954563822066,
      "flow_a_tag": "",
      "flow_b": 0.02751888158231949,
      "flow_b_tag": "",
      "flow_lb": 0.024640610441565514,
      "flow_ub": 0.03019123151898384,
      "headloss_res_a": -3.4072002757877695,
      "headloss_res_b": -3.4070347644183836
    },
    "6": {
      "flow_a": 0.039216596604130384,
      "flow_a_tag": "",
      "flow_b": 0.03921660896071372,
      "flow_b_tag": "",
      "flow_lb": 0.0390416719019413,
      "flow_ub": 0.03940384089946747,
      "headloss_res_a": -20.15786848761625,
      "headloss_res_b": -20.157881799931012
    },
    "60": {
      "flow_a": 0.017372444713687173,
      "flow_a_tag": "",
      "flow_b": 0.017372679867314434,
      "flow_b_tag": "",
      "flow_lb": 0.014521673321723938,
      "flow_ub": 0.019592784345149994,
      "headloss_res_a": -5.303915103526849,
      "headloss_res_b": -5.304059458272256
    },
    "62": {
      "flow_a": 0.007475927640716504,
      "flow_a_tag": "",
      "flow_b": 0.007476961636906823,
      "flow_b_tag": "",
      "flow_lb": 0.004098441917449236,
      "flow_ub": 0.009699055925011635,
      "headloss_res_a": -0.9727992728057764,
      "headloss_res_b": -0.9730700298095754
    },
    "64": {
      "flow_a": 0.004998684702344558,
      "flow_a_tag": "",
      "flow_b": 0.004998743371884923,
      "flow_b_tag": "",
      "flow_lb": 0.004575498402118683,
      "flow_ub": 0.005495249759405851,
      "headloss_res_a": -8.694690750994837,
      "headloss_res_b": -8.69489618001261
    },
    "66": {
      "flow_a": 0.004408450061352423,
      "flow_a_tag": "",
      "flow_b": 0.004408592859099067,
      "flow_b_tag": "",
      "flow_lb": 0.0043516443111002445,
      "flow_ub": 0.004486588295549154,
      "headloss_res_a": -6.751445302058512,
      "headloss_res_b": -6.751885598207367
    },
    "68": {
      "flow_a": 0.012472244590305331,
      "flow_a_tag": "",
      "flow_b": 0.012472579754576782,
      "flow_b_tag": "",
      "flow_lb": 0.010593310929834843,
      "flow_ub": 0.01480045635253191,
      "headloss_res_a": -2.5402594850240026,
      "headloss_res_b": -2.540397004014408
    },
    "70": {
      "flow_a": 0.011919128496665099,
      "flow_a_tag": "",
      "flow_b": 0.011919635406487505,
      "flow_b_tag": "",
      "flow_lb": 0.009873676113784313,
      "flow_ub": 0.013779793865978718,
      "headloss_res_a": -2.318415623974492,
      "headloss_res_b": -2.318614268026004
    },
    "72": {
      "flow_a": 0.003201442759881258,
      "flow_a_tag": "",
      "flow_b": 0.003200956819119334,
      "flow_b_tag": "",
      "flow_lb": 0.00036285450914874673,
      "flow_ub": 0.004793699365109205,
      "headloss_res_a": -0.16371712739333544,
      "headloss_res_b": -0.16366698039598876
    },
    "74": {
      "flow_a": 0.022546484989434682,
      "flow_a_tag": "",
      "flow_b": 0.022547403124612092,
      "flow_b_tag": "",
      "flow_lb": 0.021433977410197258,
      "flow_ub": 0.023760538548231125,
      "headloss_res_a": -8.36950522626575,
      "headloss_res_b": -8.37019137230768
    },
    "76": {
      "flow_a": 0.007209446237303851,
      "flow_a_tag": "",
      "flow_b": 0.007209369038701906,
      "flow_b_tag": "",
      "flow_lb": 0.0054750386625528336,
      "flow_ub": 0.008544033393263817,
      "headloss_res_a": -0.841752029307293,
      "headloss_res_b": -0.8417338596351522
    },
    "8": {
      "flow_a": 0.0023011485192722713,
      "flow_a_tag": "",
      "flow_b": 0.0023014536351032427,
      "flow_b_tag": "",
      "flow_lb": 0.0020796682219952345,
      "flow_ub": 0.002491282531991601,
      "headloss_res_a": -0.0344592897602483,
      "headloss_res_b": -0.03446943632789262
    }
  },
  "summary": {
    "flow_at_bounds": {
      "a_lb": 1,
      "a_ub": 0,
      "b_lb": 1,
      "b_ub": 0
    },
    "head_at_bounds": {
      "a_lb": 0,
      "a_ub": 0,
      "b_lb": 0,
      "b_ub": 0
    },
    "head_bounds_count": 19,
    "junction_count": 19,
    "min_demand_slack_a": 0.0007487014475744898,
    "min_demand_slack_b": 0.0007515525828353599,
    "pipe_count": 39,
    "total_demand_a": 0.1891200244426727,
    "total_demand_b": 0.1891200244426727,
    "total_demand_res_a": 0.0,
    "total_demand_res_b": 0.0,
    "total_demand_target": 0.1891200244426727
  }
}