{
  "junctions": {
    "100": {
      "demand_a": 0.0017271010829508493,
      "demand_b": 0.0015039067293995817,
      "demand_lb": 1e-06,
      "head_a": 106.28861327762618,
      "head_a_tag": "",
      "head_b": 106.28846100794725,
      "head_b_tag": "",
      "head_lb": 86.77221610776621,
      "head_ub": 153.2277838922338
    },
    "110": {
      "demand_a": 0.0009264081323226772,
      "demand_b": 0.0008990799850449038,
      "demand_lb": 1e-06,
      "head_a": 106.15376787388932,
      "head_a_tag": "",
      "head_b": 106.15387443013194,
      "head_b_tag": "",
      "head_lb": 86.21560255826124,
      "head_ub": 153.78439744173875
    },
    "115": {
      "demand_a": 0.011142758013290673,
      "demand_b": 0.014321637482770053,
      "demand_lb": 1e-06,
      "head_a": 105.723961970494,
      "head_a_tag": "",
      "head_b": 105.72064685045243,
      "head_b_tag": "",
      "head_lb": 79.16562740980649,
      "head_ub": 160.8343725901935
    },
    "120": {
      "demand_a": 0.020627068998942694,
      "demand_b": 0.020509230050844103,
      "demand_lb": 1e-06,
      "head_a": 105.81003628448214,
      "head_a_tag": "",
      "head_b": 105.81017173197867,
      "head_b_tag": "",
      "head_lb": 81.42322008686486,
      "head_ub": 158.57677991313514
    },
    "130": {
      "demand_a": 0.020529699371644457,
      "demand_b": 0.02054491447025385,
      "demand_lb": 1e-06,
      "head_a": 105.6057739587707,
      "head_a_tag": "",
      "head_b": 105.6054342138015,
      "head_b_tag": "",
      "head_lb": 77.894500084227,
      "head_ub": 162.105499915773
    },
    "140": {
      "demand_a": 0.018730249763785893,
      "demand_b": 0.01932100956805001,
      "demand_lb": 1e-06,
      "head_a": 105.90779292214553,
      "head_a_tag": "",
      "head_b": 105.9074110997874,
      "head_b_tag": "",
      "head_lb": 82.98206548445219,
      "head_ub": 157.0179345155478
    },
    "150": {
      "demand_a": 0.024370740543645627,
      "demand_b": 0.024707762092029524,
      "demand_lb": 1e-06,
      "head_a": 106.10523440916289,
      "head_a_tag": "",
      "head_b": 106.10294845099988,
      "head_b_tag": "",
      "head_lb": 86.31055161768435,
      "head_ub": 153.68944838231565
    },
    "160": {
      "demand_a": 0.024936107953403445,
      "demand_b": 0.025002835871883428,
      "demand_lb": 1e-06,
      "head_a": 105.85213125965122,
      "head_a_tag": "",
      "head_b": 105.85179119091298,
      "head_b_tag": "",
      "head_lb": 82.35922656162961,
      "head_ub": 157.6407734383704
    },
    "170": {
      "demand_a": 0.021069549246136857,
      "demand_b": 0.021069671902302873,
      "demand_lb": 1e-06,
      "head_a": 105.2584318027862,
      "head_a_tag": "",
      "head_b": 105.2580810769135,
      "head_b_tag": "",
      "head_lb": 71.54969951960152,
      "head_ub": 168.45030048039848
    },
    "20": {
      "demand_a": 0.0042108337687372654,
      "demand_b": 0.004208400426421843,
      "demand_lb": 1e-06,
      "head_a": 119.11434918107919,
      "head_a_tag": "",
      "head_b": 119.11434918107919,
      "head_b_tag": "",
      "head_lb": 116.00248141431898,
      "head_ub": 123.99751858568102
    },
    "30": {
      "demand_a": 0.001648597672981339,
      "demand_b": 0.0017384081544924435,
      "demand_lb": 1e-06,
      "head_a": 106.79912853137964,
      "head_a_tag": "",
      "head_b": 106.79855320365282,
      "head_b_tag": "",
      "head_lb": 88.12841938729362,
      "head_ub": 151.87158061270637
    },
    "40": {
      "demand_a": 0.0009538878176749213,
      "demand_b": 0.0009020005471538917,
      "demand_lb": 1e-06,
      "head_a": 106.64239264040279,
      "head_a_tag": "",
      "head_b": 106.64219966600028,
      "head_b_tag": "",
      "head_lb": 86.21957276930736,
      "head_ub": 153.78042723069262
    },
    "50": {
      "demand_a": 0.0009226090007554977,
      "demand_b": 0.0013804744542463693,
      "demand_lb": 1e-06,
      "head_a": 106.49970100334981,
      "head_a_tag": "",
      "head_b": 106.4991268608871,
      "head_b_tag": "",
      "head_lb": 85.28339347541171,
      "head_ub": 154.7166065245883
    },
    "55": {
      "demand_a": 0.016566622357401587,
      "demand_b": 0.01631310332446419,
      "demand_lb": 1e-06,
      "head_a": 105.78046355620108,
      "head_a_tag": "",
      "head_b": 105.80018074622272,
      "head_b_tag": "",
      "head_lb": 78.26879460181607,
      "head_ub": 161.73120539818393
    },
    "60": {
      "demand_a": 0.0006423732240036228,
      "demand_b": 0.0005004889221012984,
      "demand_lb": 1e-06,
      "head_a": 106.64595643165893,
      "head_a_tag": "",
      "head_b": 106.64619913338329,
      "head_b_tag": "",
      "head_lb": 87.73489530174572,
      "head_ub": 152.26510469825428
    },
    "70": {
      "demand_a": 0.0016091816667355152,
      "demand_b": 0.0015852131734996888,
      "demand_lb": 1e-06,
      "head_a": 106.8497879744551,
      "head_a_tag": "",
      "head_b": 106.84951947487241,
      "head_b_tag": "",
      "head_lb": 88.22899350411438,
      "head_ub": 151.77100649588562
    },
    "75": {
      "demand_a": 0.01558075921356766,
      "demand_b": 0.011711325847720363,
      "demand_lb": 1e-06,
      "head_a": 105.72472994626261,
      "head_a_tag": "",
      "head_b": 105.74603665141291,
      "head_b_tag": "",
      "head_lb": 79.57763110703831,
      "head_ub": 160.42236889296169
    },
    "80": {
      "demand_a": 0.0011114364007692862,
      "demand_b": 0.0006535190835041324,
      "demand_lb": 1e-06,
      "head_a": 106.35735226070267,
      "head_a_tag": "",
      "head_b": 106.3580990282559,
      "head_b_tag": "",
      "head_lb": 87.02947368089687,
      "head_ub": 152.97052631910313
    },
    "90": {
      "demand_a": 0.0018140402139228892,
      "demand_b": 0.002247042356490238,
      "demand_lb": 1e-06,
      "head_a": 106.40846807538664,
      "head_a_tag": "",
      "head_b": 106.40613227507369,
      "head_b_tag": "",
      "head_lb": 87.1110458474528,
      "head_ub": 152.8889541525472
    }
  },
  "metadata": {
    "DEMAND_INTERVALS": false,
    "DEMAND_LB": 1e-06,
    "FIX_TOTAL_DEMAND": true,
    "GLOBAL_SOLVER": "couenne",
    "HEADLOSS_MODEL": "hw",
    "MEASUREMENT_HEADS_EQUAL_ONLY": true,
    "MEASUREMENT_SITES": [],
    "MULTI_STARTS": 10,
    "MULTI_START_NOISE": 0.05,
    "NORM": 2,
    "PIPE_BOUNDS": true,
    "PIPE_BOUND_METHOD": "perturb",
    "PIPE_BOUND_PERTURB_BASE": "base",
    "PIPE_BOUND_PERTURB_FIX_TOTAL": true,
    "PIPE_BOUND_PERTURB_SAMPLES": 25,
    "PIPE_BOUND_PERTURB_SEED": 1,
    "PIPE_BOUND_PERTURB_SIGMA": 0.1,
    "PIPE_BOUND_POLICY": "minmax",
    "PIPE_BOUND_SAFENESS": 0.85,
    "RADIUS": true,
    "SCENARIO_SOURCE": "base",
    "SINGLE_NODE_SOLUTION": false,
    "SOLVER": "hexaly_xd",
    "USE_RESERVOIR_OUTFLOW_CONSTRAINT": false,
    "WDN_NAME": "Anytown",
    "output_dir": "data/Anytown-B-batch-20260331-165254/none",
    "timestamp": "20260331-165254"
  },
  "output_dir": "data/Anytown-B-batch-20260331-165254/none",
  "pipes": {
    "1": {
      "flow_a": 0.18912002444267273,
      "flow_a_tag": "lb",
      "flow_b": 0.18912002444267273,
      "flow_b_tag": "lb",
      "flow_lb": 0.18912002444267273,
      "flow_ub": 0.18912002444267273,
      "headloss_res_a": -3.111867766760211,
      "headloss_res_b": -3.111867766760211
    },
    "10": {
      "flow_a": 0.03621409915051371,
      "flow_a_tag": "",
      "flow_b": 0.03621004894375801,
      "flow_b_tag": "lb",
      "flow_lb": 0.03621004894375801,
      "flow_ub": 0.037094879895448685,
      "headloss_res_a": -0.8488970626365793,
      "headloss_res_b": -0.8486979036208382
    },
    "12": {
      "flow_a": 0.01969151757657528,
      "flow_a_tag": "lb",
      "flow_b": 0.019741270798681623,
      "flow_b_tag": "",
      "flow_lb": 0.01969151757657528,
      "flow_ub": 0.019883129745721817,
      "headloss_res_a": -0.7478609972384003,
      "headloss_res_b": -0.7518105335405492
    },
    "14": {
      "flow_a": 0.020959951494409195,
      "flow_a_tag": "",
      "flow_b": 0.02093155134488136,
      "flow_b_tag": "",
      "flow_lb": 0.020930293947458267,
      "flow_ub": 0.021436985582113266,
      "headloss_res_a": -0.2685211425229301,
      "headloss_res_b": -0.26775316162406876
    },
    "16": {
      "flow_a": 0.014091984413976676,
      "flow_a_tag": "",
      "flow_b": 0.014174285800355261,
      "flow_b_tag": "",
      "flow_lb": 0.013912584632635117,
      "flow_ub": 0.014262482523918152,
      "headloss_res_a": -0.3715348723947379,
      "headloss_res_b": -0.3760908976937921
    },
    "18": {
      "flow_a": 0.025289520995775024,
      "flow_a_tag": "",
      "flow_b": 0.02526566163164703,
      "flow_b_tag": "",
      "flow_lb": 0.025259651243686676,
      "flow_ub": 0.025614239275455475,
      "headloss_res_a": -0.3990451986336445,
      "headloss_res_b": -0.3982523528142855
    },
    "2": {
      "flow_a": 0.08075908190876227,
      "flow_a_tag": "",
      "flow_b": 0.08076003654914987,
      "flow_b_tag": "",
      "flow_lb": 0.0807003304362297,
      "flow_ub": 0.08126632869243622,
      "headloss_res_a": -15.163296588818731,
      "headloss_res_b": -15.163676533842764
    },
    "20": {
      "flow_a": 0.006148330556459062,
      "flow_a_tag": "",
      "flow_b": 0.00594573887065053,
      "flow_b_tag": "lb",
      "flow_lb": 0.00594573887065053,
      "flow_ub": 0.006846603937447071,
      "headloss_res_a": -0.06481635568040953,
      "headloss_res_b": -0.06038470841616629
    },
    "22": {
      "flow_a": 0.016079814644522978,
      "flow_a_tag": "",
      "flow_b": 0.016078166007117197,
      "flow_b_tag": "lb",
      "flow_lb": 0.016077831387519836,
      "flow_ub": 0.016797976568341255,
      "headloss_res_a": -0.4897269638457705,
      "headloss_res_b": -0.4896142123878765
    },
    "24": {
      "flow_a": 0.009741316575647021,
      "flow_a_tag": "",
      "flow_b": 0.00964460936477892,
      "flow_b_tag": "",
      "flow_lb": 0.009536479599773884,
      "flow_ub": 0.010511047206819057,
      "headloss_res_a": -0.17116656076974696,
      "headloss_res_b": -0.1676005268259278
    },
    "26": {
      "flow_a": 0.01979676926325353,
      "flow_a_tag": "",
      "flow_b": 0.01992081382076873,
      "flow_b_tag": "",
      "flow_lb": 0.01894422248005867,
      "flow_ub": 0.020829951390624046,
      "headloss_res_a": -0.23800168061397514,
      "headloss_res_b": -0.24116519211403464
    },
    "28": {
      "flow_a": 0.0145544477560992,
      "flow_a_tag": "",
      "flow_b": 0.014648259232731088,
      "flow_b_tag": "",
      "flow_lb": 0.014291252009570599,
      "flow_ub": 0.015310738235712051,
      "headloss_res_a": -0.3975344958212843,
      "headloss_res_b": -0.4029034983837162
    },
    "30": {
      "flow_a": 0.019063927139346126,
      "flow_a_tag": "",
      "flow_b": 0.019008885009222227,
      "flow_b_tag": "",
      "flow_lb": 0.01899469830095768,
      "flow_ub": 0.019574880599975586,
      "headloss_res_a": -1.6269833977855916,
      "headloss_res_b": -1.617536795105786
    },
    "32": {
      "flow_a": 0.019302158844882296,
      "flow_a_tag": "",
      "flow_b": 0.01927671954035759,
      "flow_b_tag": "lb",
      "flow_lb": 0.01927671954035759,
      "flow_ub": 0.019740989431738853,
      "headloss_res_a": -1.668188901641197,
      "headloss_res_b": -1.663764101000649
    },
    "34": {
      "flow_a": 0.027377910939644534,
      "flow_a_tag": "",
      "flow_b": 0.027377852422499377,
      "flow_b_tag": "",
      "flow_lb": 0.0273591261357069,
      "flow_ub": 0.028005842119455338,
      "headloss_res_a": -3.371990309498696,
      "headloss_res_b": -3.37197580031034
    },
    "36": {
      "flow_a": 0.018348271027207375,
      "flow_a_tag": "lb",
      "flow_b": 0.018374718993203698,
      "flow_b_tag": "",
      "flow_lb": 0.018348271027207375,
      "flow_ub": 0.01881066896021366,
      "headloss_res_a": -1.5063191400202158,
      "headloss_res_b": -1.510695304537365
    },
    "38": {
      "flow_a": 0.01832377441304886,
      "flow_a_tag": "",
      "flow_b": 0.01823231066333944,
      "flow_b_tag": "",
      "flow_lb": 0.017696484923362732,
      "flow_ub": 0.018880587071180344,
      "headloss_res_a": -1.5022618143654998,
      "headloss_res_b": -1.487205440306366
    },
    "4": {
      "flow_a": 0.06510826257632571,
      "flow_a_tag": "",
      "flow_b": 0.06510991283824243,
      "flow_b_tag": "",
      "flow_lb": 0.06507140398025513,
      "flow_ub": 0.06550092995166779,
      "headloss_res_a": -128.99144309166905,
      "headloss_res_b": -128.99803109319808
    },
    "40": {
      "flow_a": 0.03409574180841446,
      "flow_a_tag": "lb",
      "flow_b": 0.034141932849401785,
      "flow_b_tag": "",
      "flow_lb": 0.03409574180841446,
      "flow_ub": 0.0352771021425724,
      "headloss_res_a": -5.244650772075147,
      "headloss_res_b": -5.258961040050256
    },
    "42": {
      "flow_a": 0.012157663923374898,
      "flow_a_tag": "",
      "flow_b": 0.012094706886539576,
      "flow_b_tag": "",
      "flow_lb": 0.011307762935757637,
      "flow_ub": 0.01329136360436678,
      "headloss_res_a": -2.587447848003277,
      "headloss_res_b": -2.5605842167731203
    },
    "44": {
      "flow_a": 0.013902627196855187,
      "flow_a_tag": "",
      "flow_b": 0.013844770082047913,
      "flow_b_tag": "",
      "flow_lb": 0.013517831452190876,
      "flow_ub": 0.016134459525346756,
      "headloss_res_a": -3.3885738946534336,
      "headloss_res_b": -3.3602724781357693
    },
    "46": {
      "flow_a": 0.018659140914678574,
      "flow_a_tag": "lb",
      "flow_b": 0.018663475372126308,
      "flow_b_tag": "",
      "flow_lb": 0.018659140914678574,
      "flow_ub": 0.02026054821908474,
      "headloss_res_a": -6.123323490732686,
      "headloss_res_b": -6.126183688410467
    },
    "48": {
      "flow_a": 0.005772404465277781,
      "flow_a_tag": "",
      "flow_b": 0.005766462386242309,
      "flow_b_tag": "",
      "flow_lb": 0.005763679277151823,
      "flow_ub": 0.007044963072985411,
      "headloss_res_a": -0.23884318828416184,
      "headloss_res_b": -0.23833306453019126
    },
    "50": {
      "flow_a": 0.02748679022592097,
      "flow_a_tag": "lb",
      "flow_b": 0.027508758410321025,
      "flow_b_tag": "",
      "flow_lb": 0.027486592531204224,
      "flow_ub": 0.028059057891368866,
      "headloss_res_a": -3.3990410321106053,
      "headloss_res_b": -3.4045121338426334
    },
    "52": {
      "flow_a": 0.016401052295881624,
      "flow_a_tag": "lb",
      "flow_b": 0.016400298619734993,
      "flow_b_tag": "lb",
      "flow_lb": 0.016400272026658058,
      "flow_ub": 0.017505863681435585,
      "headloss_res_a": -4.724437559568792,
      "headloss_res_b": -4.7240006672423345
    },
    "54": {
      "flow_a": 0.0166089800950863,
      "flow_a_tag": "",
      "flow_b": 0.016507408959981637,
      "flow_b_tag": "",
      "flow_lb": 0.016385603696107864,
      "flow_ub": 0.02289876528084278,
      "headloss_res_a": -0.45033065713267656,
      "headloss_res_b": -0.44480179565808503
    },
    "56": {
      "flow_a": 0.012382963392025225,
      "flow_a_tag": "",
      "flow_b": 0.012398477528872527,
      "flow_b_tag": "",
      "flow_lb": 0.012008121237158775,
      "flow_ub": 0.015087492763996124,
      "headloss_res_a": -2.6847996088452204,
      "headloss_res_b": -2.6915681395874014
    },
    "58": {
      "flow_a": 0.024640627927176046,
      "flow_a_tag": "lb",
      "flow_b": 0.024640610441565514,
      "flow_b_tag": "lb",
      "flow_lb": 0.024640610441565514,
      "flow_ub": 0.03019123151898384,
      "headloss_res_a": -2.7276137908290545,
      "headloss_res_b": -2.7276098937899316
    },
    "6": {
      "flow_a": 0.03904184618884749,
      "flow_a_tag": "lb",
      "flow_b": 0.03904167462885861,
      "flow_b_tag": "lb",
      "flow_lb": 0.0390416719019413,
      "flow_ub": 0.03940384089946747,
      "headloss_res_a": -19.970053807230038,
      "headloss_res_b": -19.969870952620823
    },
    "60": {
      "flow_a": 0.016493891947556814,
      "flow_a_tag": "",
      "flow_b": 0.01649417350018419,
      "flow_b_tag": "",
      "flow_lb": 0.014521673321723938,
      "flow_ub": 0.019592784345149994,
      "headloss_res_a": -4.778367055734236,
      "headloss_res_b": -4.7785310692126135
    },
    "62": {
      "flow_a": 0.006137157638211056,
      "flow_a_tag": "",
      "flow_b": 0.006133851408935334,
      "flow_b_tag": "",
      "flow_lb": 0.004098441917449236,
      "flow_ub": 0.009699055925011635,
      "headloss_res_a": -0.6539851092576787,
      "headloss_res_b": -0.6532624624565768
    },
    "64": {
      "flow_a": 0.004575657298580043,
      "flow_a_tag": "lb",
      "flow_b": 0.004575498402118683,
      "flow_b_tag": "lb",
      "flow_lb": 0.004575498402118683,
      "flow_ub": 0.005495249759405851,
      "headloss_res_a": -7.276897274330125,
      "headloss_res_b": -7.276377878302592
    },
    "66": {
      "flow_a": 0.004352362126857968,
      "flow_a_tag": "lb",
      "flow_b": 0.0043516443111002445,
      "flow_b_tag": "lb",
      "flow_lb": 0.0043516443111002445,
      "flow_ub": 0.004486588295549154,
      "headloss_res_a": -6.579613200775636,
      "headloss_res_b": -6.577440181632891
    },
    "68": {
      "flow_a": 0.010593310929834843,
      "flow_a_tag": "lb",
      "flow_b": 0.010684248554153269,
      "flow_b_tag": "",
      "flow_lb": 0.010593310929834843,
      "flow_ub": 0.01480045635253191,
      "headloss_res_a": -1.8281458306406373,
      "headloss_res_b": -1.8599041819115083
    },
    "70": {
      "flow_a": 0.010569392228235492,
      "flow_a_tag": "",
      "flow_b": 0.009873676113784313,
      "flow_b_tag": "lb",
      "flow_lb": 0.009873676113784313,
      "flow_ub": 0.013779793865978718,
      "headloss_res_a": -1.8198383543610746,
      "headloss_res_b": -1.58652835665842
    },
    "72": {
      "flow_a": 0.0005494470834558309,
      "flow_a_tag": "",
      "flow_b": 0.0036373889286167847,
      "flow_b_tag": "",
      "flow_lb": 0.00036285450914874673,
      "flow_ub": 0.004793699365109205,
      "headloss_res_a": -0.004644690747506366,
      "headloss_res_b": -0.2118234833607352
    },
    "74": {
      "flow_a": 0.022127436426189584,
      "flow_a_tag": "",
      "flow_b": 0.021788141987017024,
      "flow_b_tag": "",
      "flow_lb": 0.021433977410197258,
      "flow_ub": 0.023760538548231125,
      "headloss_res_a": -8.059291159959496,
      "headloss_res_b": -7.812432679440759
    },
    "76": {
      "flow_a": 0.005560814068787997,
      "flow_a_tag": "",
      "flow_b": 0.0054750386625528336,
      "flow_b_tag": "lb",
      "flow_lb": 0.0054750386625528336,
      "flow_ub": 0.008544033393263817,
      "headloss_res_a": -0.49868305230994914,
      "headloss_res_b": -0.4833007557123534
    },
    "8": {
      "flow_a": 0.0022843320205285732,
      "flow_a_tag": "",
      "flow_b": 0.002291952288329203,
      "flow_b_tag": "",
      "flow_lb": 0.0020796682219952345,
      "flow_ub": 0.002491282531991601,
      "headloss_res_a": -0.03389933854933684,
      "headloss_res_b": -0.0341576080453737
    }
  },
  "summary": {
    "flow_at_bounds": {
      "a_lb": 12,
      "a_ub": 0,
      "b_lb": 12,
      "b_ub": 0
    },
    "head_at_bounds": {
      "a_lb": 0,
      "a_ub": 0,
      "b_lb": 0,
      "b_ub": 0
    },
    "head_bounds_count": 19,
    "junction_count": 19,
    "min_demand_slack_a": 0.0006413732240036228,
    "min_demand_slack_b": 0.0004994889221012984,
    "pipe_count": 39,
    "total_demand_a": 0.18912002444267276,
    "total_demand_b": 0.18912002444267279,
    "total_demand_res_a": 0.0,
    "total_demand_res_b": 2.7755575615628914e-17,
    "total_demand_target": 0.18912002444267276
  }
}