{
  "junctions": {
    "100": {
      "demand_a": 0.0009361136132541859,
      "demand_b": 0.0008707050680668571,
      "demand_lb": 1e-06,
      "head_a": 106.21216776163953,
      "head_a_tag": "",
      "head_b": 106.21216963928794,
      "head_b_tag": "",
      "head_lb": 86.77221610776621,
      "head_ub": 153.2277838922338
    },
    "110": {
      "demand_a": 0.0008376129928757206,
      "demand_b": 0.0009104036733932133,
      "demand_lb": 1e-06,
      "head_a": 106.04925546121518,
      "head_a_tag": "",
      "head_b": 106.04909977617994,
      "head_b_tag": "",
      "head_lb": 86.21560255826124,
      "head_ub": 153.78439744173875
    },
    "115": {
      "demand_a": 0.01643075994774633,
      "demand_b": 0.014709378803597031,
      "demand_lb": 1e-06,
      "head_a": 105.55699490741672,
      "head_a_tag": "",
      "head_b": 105.5781769363521,
      "head_b_tag": "",
      "head_lb": 79.16562740980649,
      "head_ub": 160.8343725901935
    },
    "120": {
      "demand_a": 0.022800588936587984,
      "demand_b": 0.023092743316489705,
      "demand_lb": 1e-06,
      "head_a": 105.68421907836571,
      "head_a_tag": "",
      "head_b": 105.68398938014234,
      "head_b_tag": "",
      "head_lb": 81.42322008686486,
      "head_ub": 158.57677991313514
    },
    "130": {
      "demand_a": 0.023708003763324374,
      "demand_b": 0.023763110021281664,
      "demand_lb": 1e-06,
      "head_a": 105.44084437314211,
      "head_a_tag": "",
      "head_b": 105.44084293634735,
      "head_b_tag": "",
      "head_lb": 77.894500084227,
      "head_ub": 162.105499915773
    },
    "140": {
      "demand_a": 0.014017892333902146,
      "demand_b": 0.0152169912832485,
      "demand_lb": 1e-06,
      "head_a": 105.81990243370117,
      "head_a_tag": "",
      "head_b": 105.81922109206307,
      "head_b_tag": "",
      "head_lb": 82.98206548445219,
      "head_ub": 157.0179345155478
    },
    "150": {
      "demand_a": 0.02381923539686473,
      "demand_b": 0.024043732993892893,
      "demand_lb": 1e-06,
      "head_a": 106.02571672013802,
      "head_a_tag": "",
      "head_b": 106.02521936017952,
      "head_b_tag": "",
      "head_lb": 86.31055161768435,
      "head_ub": 153.68944838231565
    },
    "160": {
      "demand_a": 0.022652565575802017,
      "demand_b": 0.022053617900253855,
      "demand_lb": 1e-06,
      "head_a": 105.74071961550314,
      "head_a_tag": "",
      "head_b": 105.74202257677938,
      "head_b_tag": "",
      "head_lb": 82.35922656162961,
      "head_ub": 157.6407734383704
    },
    "170": {
      "demand_a": 0.02228005377763622,
      "demand_b": 0.022280424780034825,
      "demand_lb": 1e-06,
      "head_a": 105.06126578479832,
      "head_a_tag": "",
      "head_b": 105.0611666954794,
      "head_b_tag": "",
      "head_lb": 71.54969951960152,
      "head_ub": 168.45030048039848
    },
    "20": {
      "demand_a": 0.0036287173506499015,
      "demand_b": 0.0036282235526875484,
      "demand_lb": 1e-06,
      "head_a": 119.11434918107919,
      "head_a_tag": "",
      "head_b": 119.11434918107919,
      "head_b_tag": "",
      "head_lb": 116.00248141431898,
      "head_ub": 123.99751858568102
    },
    "30": {
      "demand_a": 0.0008283949555065867,
      "demand_b": 0.0010179771433826423,
      "demand_lb": 1e-06,
      "head_a": 106.73458682056143,
      "head_a_tag": "",
      "head_b": 106.7345954875302,
      "head_b_tag": "",
      "head_lb": 88.12841938729362,
      "head_ub": 151.87158061270637
    },
    "40": {
      "demand_a": 0.0010579904453370294,
      "demand_b": 0.0008076597853906679,
      "demand_lb": 1e-06,
      "head_a": 106.57321850742618,
      "head_a_tag": "",
      "head_b": 106.57481142076028,
      "head_b_tag": "",
      "head_lb": 86.21957276930736,
      "head_ub": 153.78042723069262
    },
    "50": {
      "demand_a": 0.0005454068310605381,
      "demand_b": 0.001347694018177012,
      "demand_lb": 1e-06,
      "head_a": 106.42760445294878,
      "head_a_tag": "",
      "head_b": 106.42706600029251,
      "head_b_tag": "",
      "head_lb": 85.28339347541171,
      "head_ub": 154.7166065245883
    },
    "55": {
      "demand_a": 0.0157423653344244,
      "demand_b": 0.01530662252746739,
      "demand_lb": 1e-06,
      "head_a": 105.66804473091251,
      "head_a_tag": "",
      "head_b": 105.68153225424467,
      "head_b_tag": "",
      "head_lb": 78.26879460181607,
      "head_ub": 161.73120539818393
    },
    "60": {
      "demand_a": 0.0010489090264744205,
      "demand_b": 0.0009020058844213391,
      "demand_lb": 1e-06,
      "head_a": 106.57642660061795,
      "head_a_tag": "",
      "head_b": 106.57815169431508,
      "head_b_tag": "",
      "head_lb": 87.73489530174572,
      "head_ub": 152.26510469825428
    },
    "70": {
      "demand_a": 0.0010445603947898952,
      "demand_b": 0.0011164658903222158,
      "demand_lb": 1e-06,
      "head_a": 106.785467221383,
      "head_a_tag": "",
      "head_b": 106.78539478587004,
      "head_b_tag": "",
      "head_lb": 88.22899350411438,
      "head_ub": 151.77100649588562
    },
    "75": {
      "demand_a": 0.015652160806037808,
      "demand_b": 0.016730549480820655,
      "demand_lb": 1e-06,
      "head_a": 105.58164535725447,
      "head_a_tag": "",
      "head_b": 105.59036395156879,
      "head_b_tag": "",
      "head_lb": 79.57763110703831,
      "head_ub": 160.42236889296169
    },
    "80": {
      "demand_a": 0.0014586142358213317,
      "demand_b": 6.058890075683748e-05,
      "demand_lb": 1e-06,
      "head_a": 106.2819932232646,
      "head_a_tag": "",
      "head_b": 106.2872417434029,
      "head_b_tag": "",
      "head_lb": 87.02947368089687,
      "head_ub": 152.97052631910313
    },
    "90": {
      "demand_a": 0.0006300787245770781,
      "demand_b": 0.0012611294189878997,
      "demand_lb": 1e-06,
      "head_a": 106.34083209328797,
      "head_a_tag": "",
      "head_b": 106.33944270736397,
      "head_b_tag": "",
      "head_lb": 87.1110458474528,
      "head_ub": 152.8889541525472
    }
  },
  "metadata": {
    "DEMAND_INTERVALS": false,
    "DEMAND_LB": 1e-06,
    "FIX_TOTAL_DEMAND": true,
    "GLOBAL_SOLVER": "couenne",
    "HEADLOSS_MODEL": "hw",
    "MEASUREMENT_HEADS_EQUAL_ONLY": true,
    "MEASUREMENT_SITES": [
      "100",
      "130"
    ],
    "MULTI_STARTS": 10,
    "MULTI_START_NOISE": 0.05,
    "NORM": 2,
    "PIPE_BOUNDS": true,
    "PIPE_BOUND_METHOD": "perturb",
    "PIPE_BOUND_PERTURB_BASE": "base",
    "PIPE_BOUND_PERTURB_FIX_TOTAL": true,
    "PIPE_BOUND_PERTURB_SAMPLES": 25,
    "PIPE_BOUND_PERTURB_SEED": 1,
    "PIPE_BOUND_PERTURB_SIGMA": 0.1,
    "PIPE_BOUND_POLICY": "minmax",
    "PIPE_BOUND_SAFENESS": 0.85,
    "RADIUS": true,
    "SCENARIO_SOURCE": "base",
    "SINGLE_NODE_SOLUTION": false,
    "SOLVER": "hexaly_xd",
    "USE_RESERVOIR_OUTFLOW_CONSTRAINT": false,
    "WDN_NAME": "Anytown",
    "output_dir": "data/Anytown-B-batch-20260331-165254/100_130",
    "timestamp": "20260331-165254"
  },
  "output_dir": "data/Anytown-B-batch-20260331-165254/100_130",
  "pipes": {
    "1": {
      "flow_a": 0.18912002444267273,
      "flow_a_tag": "lb",
      "flow_b": 0.18912002444267273,
      "flow_b_tag": "lb",
      "flow_lb": 0.18912002444267273,
      "flow_ub": 0.18912002444267273,
      "headloss_res_a": -3.111867766760211,
      "headloss_res_b": -3.111867766760211
    },
    "10": {
      "flow_a": 0.03663450681630332,
      "flow_a_tag": "",
      "flow_b": 0.036631942648036674,
      "flow_b_tag": "",
      "flow_lb": 0.03621004894375801,
      "flow_ub": 0.037094879895448685,
      "headloss_res_a": -0.869701236939489,
      "headloss_res_b": -0.8695735565474603
    },
    "12": {
      "flow_a": 0.01977125273894205,
      "flow_a_tag": "",
      "flow_b": 0.01980285100852075,
      "flow_b_tag": "",
      "flow_lb": 0.01969151757657528,
      "flow_ub": 0.019883129745721817,
      "headloss_res_a": -0.7541957612866463,
      "headloss_res_b": -0.7567137982357475
    },
    "14": {
      "flow_a": 0.021247499075962774,
      "flow_a_tag": "",
      "flow_b": 0.02114864971292574,
      "flow_b_tag": "",
      "flow_lb": 0.020930293947458267,
      "flow_ub": 0.021436985582113266,
      "headloss_res_a": -0.27636128842604796,
      "headloss_res_b": -0.2736528701611632
    },
    "16": {
      "flow_a": 0.014031204381030728,
      "flow_a_tag": "",
      "flow_b": 0.014130952166871283,
      "flow_b_tag": "",
      "flow_lb": 0.013912584632635117,
      "flow_ub": 0.014262482523918152,
      "headloss_res_a": -0.3681865037576496,
      "headloss_res_b": -0.3736870923689952
    },
    "18": {
      "flow_a": 0.02556405978649727,
      "flow_a_tag": "",
      "flow_b": 0.0253984187985299,
      "flow_b_tag": "",
      "flow_lb": 0.025259651243686676,
      "flow_ub": 0.025614239275455475,
      "headloss_res_a": -0.4082270431190206,
      "headloss_res_b": -0.4026742666552672
    },
    "2": {
      "flow_a": 0.08098749795520635,
      "flow_a_tag": "",
      "flow_b": 0.08098775487895984,
      "flow_b_tag": "",
      "flow_lb": 0.0807003304362297,
      "flow_ub": 0.08126632869243622,
      "headloss_res_a": -15.254347157167377,
      "headloss_res_b": -15.254449731333146
    },
    "20": {
      "flow_a": 0.006633760982984656,
      "flow_a_tag": "",
      "flow_b": 0.006218901524937839,
      "flow_b_tag": "",
      "flow_lb": 0.00594573887065053,
      "flow_ub": 0.006846603937447071,
      "headloss_res_a": -0.07612240990269317,
      "headloss_res_b": -0.0664078351457558
    },
    "22": {
      "flow_a": 0.016416996627181976,
      "flow_a_tag": "",
      "flow_b": 0.01639175535514931,
      "flow_b_tag": "",
      "flow_lb": 0.016077831387519836,
      "flow_ub": 0.016797976568341255,
      "headloss_res_a": -0.5114495417545296,
      "headloss_res_b": -0.5098018204811816
    },
    "24": {
      "flow_a": 0.010121620785229065,
      "flow_a_tag": "",
      "flow_b": 0.010062016876316983,
      "flow_b_tag": "",
      "flow_lb": 0.009536479599773884,
      "flow_ub": 0.010511047206819057,
      "headloss_res_a": -0.18552372580848298,
      "headloss_res_b": -0.1832255215126689
    },
    "26": {
      "flow_a": 0.019975165816175366,
      "flow_a_tag": "",
      "flow_b": 0.02000402769992885,
      "flow_b_tag": "",
      "flow_lb": 0.01894422248005867,
      "flow_ub": 0.020829951390624046,
      "headloss_res_a": -0.24255818097911125,
      "headloss_res_b": -0.24329957984415157
    },
    "28": {
      "flow_a": 0.014683441277852694,
      "flow_a_tag": "",
      "flow_b": 0.01486006839500229,
      "flow_b_tag": "",
      "flow_lb": 0.014291252009570599,
      "flow_ub": 0.015310738235712051,
      "headloss_res_a": -0.4049423841896699,
      "headloss_res_b": -0.41519978455209383
    },
    "30": {
      "flow_a": 0.019396674118039647,
      "flow_a_tag": "",
      "flow_b": 0.01928272713689678,
      "flow_b_tag": "",
      "flow_lb": 0.01899469830095768,
      "flow_ub": 0.019574880599975586,
      "headloss_res_a": -1.6846802430276222,
      "headloss_res_b": -1.6648085028448383
    },
    "32": {
      "flow_a": 0.019608132456199683,
      "flow_a_tag": "",
      "flow_b": 0.01950395252746987,
      "flow_b_tag": "",
      "flow_lb": 0.01927671954035759,
      "flow_ub": 0.019740989431738853,
      "headloss_res_a": -1.721871664162266,
      "headloss_res_b": -1.7034973955306016
    },
    "34": {
      "flow_a": 0.02774875869975826,
      "flow_a_tag": "",
      "flow_b": 0.027775451461864692,
      "flow_b_tag": "",
      "flow_lb": 0.0273591261357069,
      "flow_ub": 0.028005842119455338,
      "headloss_res_a": -3.4645715571016797,
      "headloss_res_b": -3.4712839775359687
    },
    "36": {
      "flow_a": 0.018550142010862653,
      "flow_a_tag": "",
      "flow_b": 0.018696292742079203,
      "flow_b_tag": "",
      "flow_lb": 0.018348271027207375,
      "flow_ub": 0.01881066896021366,
      "headloss_res_a": -1.5398817593447327,
      "headloss_res_b": -1.5644140004765639
    },
    "38": {
      "flow_a": 0.018549914443842987,
      "flow_a_tag": "",
      "flow_b": 0.018148099169169252,
      "flow_b_tag": "",
      "flow_lb": 0.017696484923362732,
      "flow_ub": 0.018880587071180344,
      "headloss_res_a": -1.5398432301789229,
      "headloss_res_b": -1.4734027666109262
    },
    "4": {
      "flow_a": 0.06529228130029587,
      "flow_a_tag": "",
      "flow_b": 0.06529226265045951,
      "flow_b_tag": "",
      "flow_lb": 0.06507140398025513,
      "flow_ub": 0.06550092995166779,
      "headloss_res_a": -129.7267942917715,
      "headloss_res_b": -129.72672177721023
    },
    "40": {
      "flow_a": 0.034605679699650886,
      "flow_a_tag": "",
      "flow_b": 0.03484476219687786,
      "flow_b_tag": "",
      "flow_lb": 0.03409574180841446,
      "flow_ub": 0.0352771021425724,
      "headloss_res_a": -5.403718895974568,
      "headloss_res_b": -5.479120012743107
    },
    "42": {
      "flow_a": 0.012433632726533455,
      "flow_a_tag": "",
      "flow_b": 0.012439794608525621,
      "flow_b_tag": "",
      "flow_lb": 0.011307762935757637,
      "flow_ub": 0.01329136360436678,
      "headloss_res_a": -2.7069392860687116,
      "headloss_res_b": -2.709643035037548
    },
    "44": {
      "flow_a": 0.014822735597811849,
      "flow_a_tag": "",
      "flow_b": 0.014772323847661943,
      "flow_b_tag": "",
      "flow_lb": 0.013517831452190876,
      "flow_ub": 0.016134459525346756,
      "headloss_res_a": -3.854660274029177,
      "headloss_res_b": -3.828350736343997
    },
    "46": {
      "flow_a": 0.019451929629744225,
      "flow_a_tag": "",
      "flow_b": 0.019422924890709743,
      "flow_b_tag": "",
      "flow_lb": 0.018659140914678574,
      "flow_ub": 0.02026054821908474,
      "headloss_res_a": -6.657624720729638,
      "headloss_res_b": -6.637681358212079
    },
    "48": {
      "flow_a": 0.006392918542358612,
      "flow_a_tag": "",
      "flow_b": 0.006396301865648206,
      "flow_b_tag": "",
      "flow_lb": 0.005763679277151823,
      "flow_ub": 0.007044963072985411,
      "headloss_res_a": -0.29543499543894547,
      "headloss_res_b": -0.2957627032678928
    },
    "50": {
      "flow_a": 0.0278244924917719,
      "flow_a_tag": "",
      "flow_b": 0.0277533869009418,
      "flow_b_tag": "",
      "flow_lb": 0.027486592531204224,
      "flow_ub": 0.028059057891368866,
      "headloss_res_a": -3.483633333871041,
      "headloss_res_b": -3.4657349413100014
    },
    "52": {
      "flow_a": 0.016942340894231578,
      "flow_a_tag": "",
      "flow_b": 0.016944294651879035,
      "flow_b_tag": "",
      "flow_lb": 0.016400272026658058,
      "flow_ub": 0.017505863681435585,
      "headloss_res_a": -5.04318555980818,
      "headloss_res_b": -5.044358949714014
    },
    "54": {
      "flow_a": 0.019469800224729373,
      "flow_a_tag": "",
      "flow_b": 0.01975322034777559,
      "flow_b_tag": "",
      "flow_lb": 0.016385603696107864,
      "flow_ub": 0.02289876528084278,
      "headloss_res_a": -0.6201706939394455,
      "headloss_res_b": -0.6384819074884801
    },
    "56": {
      "flow_a": 0.013611552182372963,
      "flow_a_tag": "",
      "flow_b": 0.013604771683164919,
      "flow_b_tag": "",
      "flow_lb": 0.012008121237158775,
      "flow_ub": 0.015087492763996124,
      "headloss_res_a": -3.247409313535447,
      "headloss_res_b": -3.244160622061098
    },
    "58": {
      "flow_a": 0.027400007226977868,
      "flow_a_tag": "",
      "flow_b": 0.02746429751909086,
      "flow_b_tag": "",
      "flow_lb": 0.024640610441565514,
      "flow_ub": 0.03019123151898384,
      "headloss_res_a": -3.3774712754735043,
      "headloss_res_b": -3.3934438832379863
    },
    "6": {
      "flow_a": 0.039211527836520585,
      "flow_a_tag": "",
      "flow_b": 0.03921178336056584,
      "flow_b_tag": "",
      "flow_lb": 0.0390416719019413,
      "flow_ub": 0.03940384089946747,
      "headloss_res_a": -20.152406259354663,
      "headloss_res_b": -20.152683503006067
    },
    "60": {
      "flow_a": 0.01730355564602646,
      "flow_a_tag": "",
      "flow_b": 0.017305959180974117,
      "flow_b_tag": "",
      "flow_lb": 0.014521673321723938,
      "flow_ub": 0.019592784345149994,
      "headloss_res_a": -5.261710840926671,
      "headloss_res_b": -5.263180493790305
    },
    "62": {
      "flow_a": 0.007423215308181278,
      "flow_a_tag": "",
      "flow_b": 0.007322500127806826,
      "flow_b_tag": "",
      "flow_lb": 0.004098441917449236,
      "flow_ub": 0.009699055925011635,
      "headloss_res_a": -0.9590429145201533,
      "headloss_res_b": -0.9330458807202056
    },
    "64": {
      "flow_a": 0.00497649813160976,
      "flow_a_tag": "",
      "flow_b": 0.004974465599060708,
      "flow_b_tag": "",
      "flow_lb": 0.004575498402118683,
      "flow_ub": 0.005495249759405851,
      "headloss_res_a": -8.617176360231882,
      "headloss_res_b": -8.610101519955498
    },
    "66": {
      "flow_a": 0.004414725658643412,
      "flow_a_tag": "",
      "flow_b": 0.0044152943535673795,
      "flow_b_tag": "",
      "flow_lb": 0.0043516443111002445,
      "flow_ub": 0.004486588295549154,
      "headloss_res_a": -6.770808280644858,
      "headloss_res_b": -6.772566479950673
    },
    "68": {
      "flow_a": 0.012850871313627882,
      "flow_a_tag": "",
      "flow_b": 0.012262322688074808,
      "flow_b_tag": "",
      "flow_lb": 0.010593310929834843,
      "flow_ub": 0.01480045635253191,
      "headloss_res_a": -2.697998846584849,
      "headloss_res_b": -2.4548634662489297
    },
    "70": {
      "flow_a": 0.012185560997506685,
      "flow_a_tag": "",
      "flow_b": 0.011923571460780016,
      "flow_b_tag": "",
      "flow_lb": 0.009873676113784313,
      "flow_ub": 0.013779793865978718,
      "headloss_res_a": -2.4240036246284977,
      "headloss_res_b": -2.320156991012889
    },
    "72": {
      "flow_a": 0.003579888634118448,
      "flow_a_tag": "",
      "flow_b": 0.002447056115522223,
      "flow_b_tag": "",
      "flow_lb": 0.00036285450914874673,
      "flow_ub": 0.004793699365109205,
      "headloss_res_a": -0.20512231938705527,
      "headloss_res_b": -0.09517419112119006
    },
    "74": {
      "flow_a": 0.022788853777073972,
      "flow_a_tag": "",
      "flow_b": 0.022560656663030254,
      "flow_b_tag": "",
      "flow_lb": 0.021433977410197258,
      "flow_ub": 0.023760538548231125,
      "headloss_res_a": -8.551615275231637,
      "headloss_res_b": -8.380099233037932
    },
    "76": {
      "flow_a": 0.0070464884426495724,
      "flow_a_tag": "",
      "flow_b": 0.007254034135562864,
      "flow_b_tag": "",
      "flow_lb": 0.0054750386625528336,
      "flow_ub": 0.008544033393263817,
      "headloss_res_a": -0.8038363408147471,
      "headloss_res_b": -0.8522813202987135
    },
    "8": {
      "flow_a": 0.002289678929208308,
      "flow_a_tag": "",
      "flow_b": 0.002287845619154468,
      "flow_b_tag": "",
      "flow_lb": 0.0020796682219952345,
      "flow_ub": 0.002491282531991601,
      "headloss_res_a": -0.03407469554622708,
      "headloss_res_b": -0.034019808062372606
    }
  },
  "summary": {
    "flow_at_bounds": {
      "a_lb": 1,
      "a_ub": 0,
      "b_lb": 1,
      "b_ub": 0
    },
    "head_at_bounds": {
      "a_lb": 0,
      "a_ub": 0,
      "b_lb": 0,
      "b_ub": 0
    },
    "head_bounds_count": 19,
    "junction_count": 19,
    "min_demand_slack_a": 0.0005444068310605381,
    "min_demand_slack_b": 5.9588900756837485e-05,
    "pipe_count": 39,
    "total_demand_a": 0.1891200244426727,
    "total_demand_b": 0.18912002444267279,
    "total_demand_res_a": 0.0,
    "total_demand_res_b": 8.326672684688674e-17,
    "total_demand_target": 0.1891200244426727
  }
}